ota42y_python_package_test/cxt.cpython-38-x86_64-linux-gnu.so
ota42y_python_package_test-0.1.7.dist-info/LICENSE
ota42y_python_package_test-0.1.7.dist-info/METADATA
ota42y_python_package_test-0.1.7.dist-info/WHEEL
ota42y_python_package_test-0.1.7.dist-info/top_level.txt
ota42y_python_package_test-0.1.7.dist-info/RECORD
